standup/__init__.py
standup/codebase/__init__.py
standup/codebase/parser.py
standup-0.1.2.data/scripts/standup_codebase.py
standup-0.1.2.dist-info/DESCRIPTION.rst
standup-0.1.2.dist-info/METADATA
standup-0.1.2.dist-info/metadata.json
standup-0.1.2.dist-info/RECORD
standup-0.1.2.dist-info/top_level.txt
standup-0.1.2.dist-info/WHEEL
