Metadata-Version: 2.0
Name: standup
Version: 0.1.2
Summary: "What the FUCK did I do today?"
Home-page: http://github.com/beaumartinez/standup/
Author: Beau Martinez
Author-email: beau@beaumartinez.com
License: WTFPL
Platform: UNKNOWN
Classifier: Programming Language :: Python :: 3.4
Requires-Dist: requests (>=2.2.1)
